spoteno/__init__.py
spoteno/normalizer.py
spoteno/configuration/__init__.py
spoteno/configuration/base.py
spoteno/configuration/de.py
spoteno/resources/__init__.py
spoteno/resources/de/alphabet.json
spoteno/steps/__init__.py
spoteno/steps/base.py
spoteno/steps/diacritics.py
spoteno/steps/numbers.py
spoteno/steps/replacement.py
spoteno/steps/string.py
spoteno/steps/tokenize.py
spoteno-0.1.1.dist-info/LICENSE
spoteno-0.1.1.dist-info/METADATA
spoteno-0.1.1.dist-info/WHEEL
spoteno-0.1.1.dist-info/top_level.txt
spoteno-0.1.1.dist-info/RECORD
