Metadata-Version: 2.1
Name: spoteno
Version: 0.1.1
Summary: spoteno is a library for spoken text normalization for ASR
Home-page: https://github.com/ynop/spoteno
Author: Matthias Buechi
Author-email: buec@zhaw.ch
License: MIT
Download-URL: https://github.com/ynop/spoteno/releases
Keywords: ASR speech recognition spoken text normalization transcripts
Platform: UNKNOWN
Classifier: Intended Audience :: Science/Research
Classifier: License :: OSI Approved :: MIT License
Classifier: Programming Language :: Python :: 3 :: Only
Classifier: Topic :: Scientific/Engineering :: Human Machine Interfaces
Requires-Dist: tqdm (==4.39.0)
Requires-Dist: num2words (==0.5.10)
Provides-Extra: ci
Requires-Dist: flake8 (==3.7.9) ; extra == 'ci'
Requires-Dist: flake8-quotes (==2.1.1) ; extra == 'ci'
Provides-Extra: dev
Requires-Dist: click (==7.0) ; extra == 'dev'
Requires-Dist: pytest (==5.2.3) ; extra == 'dev'
Requires-Dist: pytest-runner (==5.2) ; extra == 'dev'
Requires-Dist: pytest-cov (==2.8.1) ; extra == 'dev'
Requires-Dist: pytest-benchmark (==3.2.2) ; extra == 'dev'
Requires-Dist: bump2version ; extra == 'dev'
